{
  "session_id": "composite_C56",
  "nodes": {
    "topic_turn_0": {
      "node_id": "topic_turn_0",
      "node_type": "topic",
      "label": "turn_0",
      "properties": {
        "content_length": 62,
        "detected_at": "2026-02-28T21:22:48.234450"
      },
      "created_at": "2026-02-28T21:22:48.234463",
      "updated_at": "2026-02-28T21:22:48.234464"
    }
  },
  "edges": {},
  "metadata": {
    "turn_count": 1,
    "last_content_length": 62
  },
  "last_updated": "2026-02-28T21:22:48.234450"
}