{
  "projects": [
    {
      "id": "proj-001",
      "name": "Q2 新品上市計畫",
      "description": "第二季新產品線上市，含產品目錄、經銷通路、行銷活動",
      "status": "active",
      "progress": 35,
      "start_date": "2026-02-15",
      "target_date": "2026-04-30",
      "task_ids": ["task-002", "task-003", "task-006"],
      "customer_ids": ["cust-001", "cust-002"]
    },
    {
      "id": "proj-002",
      "name": "官網改版專案",
      "description": "公司官網全面改版，提升品牌形象和線上詢價功能",
      "status": "planning",
      "progress": 10,
      "start_date": "2026-03-01",
      "target_date": "2026-05-15",
      "task_ids": ["task-008"],
      "customer_ids": []
    }
  ]
}
