{
  "id": "31c451f7-a272-4231-9338-43a6e1ab6c98",
  "content": "[失敗經驗] 任務：[群組近期對話紀錄]\n  49:07 吳明憲(Alan Wu): [檔案: az-900.png] \n  49:07 吳明憲(Alan Wu): [檔案: MCP.png] \n  49:07 吳明憲(\n失敗類型：general_failure\n回應片段：L2 回報：Telegram reply 工具目前不可用（MCP 插件未連接），無法在群組中回覆。\n\n這跟 Zeal 說的吻合——Telegram 正在做大優化，10 個區塊要 debug，所以插件暫時斷線。目前我在群組是「靜默狀態」，等 Telegram MCP 重新上線後才能回覆。",
  "layer": "L1_short",
  "tags": [],
  "quality_tier": "gold",
  "dna27_routing": {},
  "created_at": "2026-03-25T21:26:47.882747+08:00",
  "updated_at": "2026-03-25T21:26:47.882747+08:00",
  "access_count": 0,
  "relevance_score": 1.0,
  "source": "backfill",
  "outcome": "",
  "user_id": "6969045906",
  "session_id": "",
  "dept_id": "",
  "chat_scope": "",
  "group_id": "",
  "archived": false
}