{
  "session_id": "e2e_sc05_topic_1773514513",
  "nodes": {
    "topic_turn_0": {
      "node_id": "topic_turn_0",
      "node_type": "topic",
      "label": "turn_0",
      "properties": {
        "content_length": 27,
        "detected_at": "2026-03-15T02:55:13.643639"
      },
      "created_at": "2026-03-15T02:55:13.643668",
      "updated_at": "2026-03-15T02:55:13.643670"
    }
  },
  "edges": {},
  "metadata": {
    "turn_count": 1,
    "last_content_length": 27
  },
  "last_updated": "2026-03-15T02:55:13.643639"
}